oasma/__init__.py
oasma/templates/component.md.jinja
oasma/templates/response.md.jinja
oasma/templates/template.md.jinja
oasma-0.1.0.dist-info/METADATA
oasma-0.1.0.dist-info/WHEEL
oasma-0.1.0.dist-info/entry_points.txt
oasma-0.1.0.dist-info/licenses/LICENSE
oasma-0.1.0.dist-info/RECORD
