Metadata-Version: 2.4
Name: oasma
Version: 0.1.0
Summary: OpenAPI to single markdown file converter for in-tree documentation
Author-email: fregrem <fx@fregrem.de>
License-Expression: GPL-3.0-or-later
License-File: LICENSE
Requires-Python: >=3.7
Requires-Dist: jinja2
